nucdiff/__init__.py
nucdiff/__version__.py
nucdiff/class_errors.py
nucdiff/class_interv_coord.py
nucdiff/class_nucmer.py
nucdiff/find_errors.py
nucdiff/general.py
nucdiff/generate_output.py
nucdiff/initial_preparation.py
nucdiff/nucdiff.py
nucdiff/ref_coord.py
nucdiff/statistics.py
NucDiff-2.0.3.dist-info/LICENSE
NucDiff-2.0.3.dist-info/METADATA
NucDiff-2.0.3.dist-info/WHEEL
NucDiff-2.0.3.dist-info/entry_points.txt
NucDiff-2.0.3.dist-info/top_level.txt
NucDiff-2.0.3.dist-info/RECORD
