Metadata-Version: 2.1
Name: NucDiff
Version: 2.0.3
Summary: NucDiff locates and categorizes differences between two closely related nucleotide sequences.
Home-page: https://github.com/uio-cels/NucDiff
Author: Ksenia Khelik
Author-email: kseniakh@ifi.uio.no
Maintainer: zach.charlop.powers@gmail.com
Maintainer-email: zach.charlop.powers@gmail.com
License: Mozilla Public License Version 2.0
Platform: UNKNOWN
Classifier: License :: OSI Approved :: Mozilla Public License 2.0 (MPL 2.0)
Classifier: Programming Language :: Python
Classifier: Programming Language :: Python :: 2.7
Classifier: Programming Language :: Python :: 3
Classifier: Programming Language :: Python :: 3.3
Classifier: Programming Language :: Python :: 3.4
Classifier: Programming Language :: Python :: 3.5
Classifier: Programming Language :: Python :: 3.6
Classifier: Programming Language :: Python :: Implementation :: CPython
Requires-Dist: biopython
